osdu/__init__.py
osdu/client.py
osdu/serviceclientbase.py
osdu/entitlements/__init__.py
osdu/entitlements/_client.py
osdu/identity/__init__.py
osdu/identity/consts.py
osdu/identity/exceptions.py
osdu/identity/_credential/__init__.py
osdu/identity/_credential/base.py
osdu/identity/_credential/environment.py
osdu/identity/_credential/msal_interactive.py
osdu/identity/_credential/msal_non_interactive.py
osdu/identity/_credential/token.py
osdu/search/__init__.py
osdu/search/_client.py
osdu_sdk-0.0.14.dist-info/LICENSE.md
osdu_sdk-0.0.14.dist-info/METADATA
osdu_sdk-0.0.14.dist-info/WHEEL
osdu_sdk-0.0.14.dist-info/top_level.txt
osdu_sdk-0.0.14.dist-info/RECORD
