Metadata-Version: 2.1
Name: osdu-sdk
Version: 0.0.14
Summary: OSDU SDK for Python
Home-page: https://github.com/equinor/osdu-sdk-python
Author: Equinor ASA
Author-email: mhew@equinor.com
License: MIT
Project-URL: Issue Tracker, https://github.com/equinor/osdu-sdk-python/issues
Keywords: osdu sdk python
Classifier: Development Status :: 5 - Production/Stable
Classifier: Intended Audience :: Developers
Classifier: Topic :: Software Development :: Build Tools
Classifier: Environment :: Console
Classifier: License :: OSI Approved :: MIT License
Classifier: Natural Language :: English
Classifier: Programming Language :: Python :: 3.8
Classifier: Programming Language :: Python :: 3.9
Classifier: Programming Language :: Python :: 3.10
Requires-Python: >=3.8
License-File: LICENSE.md
Requires-Dist: requests
Requires-Dist: msal
